dbms/__init__.py
dbms/__version__.py
dbms/mongodb.py
dbms/mongodb2.py
dbms/triggers.py
adbms-0.1.1.dist-info/METADATA
adbms-0.1.1.dist-info/WHEEL
adbms-0.1.1.dist-info/top_level.txt
adbms-0.1.1.dist-info/RECORD
