Metadata-Version: 2.4
Name: adbms
Version: 0.1.1
Summary: Simple Oracle Trigger & MongoDB practice snippets for students
Author: Your Name
Author-email: your@email.com
License: MIT
Keywords: dbms,oracle,triggers,mongodb,practice
Requires-Python: >=3.7
Dynamic: author
Dynamic: author-email
Dynamic: keywords
Dynamic: license
Dynamic: requires-python
Dynamic: summary
